linebot_error_analyzer/__init__.py
linebot_error_analyzer/analyzer.py
linebot_error_analyzer/async_analyzer.py
linebot_error_analyzer/exceptions.py
linebot_error_analyzer/py.typed
linebot_error_analyzer/core/__init__.py
linebot_error_analyzer/core/base_analyzer.py
linebot_error_analyzer/database/__init__.py
linebot_error_analyzer/database/error_database.py
linebot_error_analyzer/models/__init__.py
linebot_error_analyzer/models/enums.py
linebot_error_analyzer/models/error_info.py
linebot_error_analyzer/models/log_parser.py
linebot_error_analyzer/utils/__init__.py
linebot_error_analyzer/utils/types.py
linebot_error_analyzer-3.0.1.dist-info/licenses/LICENSE
linebot_error_analyzer-3.0.1.dist-info/METADATA
linebot_error_analyzer-3.0.1.dist-info/WHEEL
linebot_error_analyzer-3.0.1.dist-info/top_level.txt
linebot_error_analyzer-3.0.1.dist-info/RECORD
