Metadata-Version: 2.4
Name: linebot-error-analyzer
Version: 3.0.1
Summary: LINE Bot SDK のエラーを自動分析・診断するライブラリ
Home-page: https://github.com/raiton-boo/linebot-error-analyzer
Author: らいとん
Author-email: raitosongwe@gmail.com
License: MIT
Project-URL: Bug Reports, https://github.com/raiton-boo/linebot-error-analyzer/issues
Project-URL: Source, https://github.com/raiton-boo/linebot-error-analyzer
Project-URL: Documentation, https://github.com/raiton-boo/linebot-error-analyzer/tree/main/docs
Project-URL: Changelog, https://github.com/raiton-boo/linebot-error-analyzer/releases
Keywords: linebot,bot,error,analyzer,messaging-api,webhook,diagnostics,line,chatbot
Platform: any
Classifier: Development Status :: 5 - Production/Stable
Classifier: Intended Audience :: Developers
Classifier: Programming Language :: Python :: 3
Classifier: Programming Language :: Python :: 3.9
Classifier: Programming Language :: Python :: 3.10
Classifier: Programming Language :: Python :: 3.11
Classifier: Programming Language :: Python :: 3.12
Classifier: Programming Language :: Python :: 3.13
Classifier: Topic :: Software Development :: Libraries :: Python Modules
Classifier: Topic :: Communications :: Chat
Classifier: Topic :: Internet :: WWW/HTTP
Classifier: Topic :: Software Development :: Bug Tracking
Classifier: Operating System :: OS Independent
Requires-Python: >=3.9
License-File: LICENSE
Requires-Dist: typing_extensions>=4.0.0
Provides-Extra: dev
Requires-Dist: pytest>=8.0.0; extra == "dev"
Requires-Dist: pytest-asyncio>=0.23.0; extra == "dev"
Requires-Dist: pytest-cov>=4.0.0; extra == "dev"
Requires-Dist: psutil>=5.9.0; extra == "dev"
Requires-Dist: typing_extensions>=4.0.0; extra == "dev"
Provides-Extra: quality
Requires-Dist: black>=24.0.0; extra == "quality"
Requires-Dist: flake8>=7.0.0; extra == "quality"
Requires-Dist: mypy>=1.8.0; extra == "quality"
Provides-Extra: docs
Requires-Dist: sphinx>=7.0.0; extra == "docs"
Requires-Dist: sphinx-rtd-theme>=2.0.0; extra == "docs"
Provides-Extra: line-sdk
Requires-Dist: line-bot-sdk>=3.0.0; extra == "line-sdk"
Provides-Extra: all
Requires-Dist: pytest>=8.0.0; extra == "all"
Requires-Dist: pytest-asyncio>=0.23.0; extra == "all"
Requires-Dist: pytest-cov>=4.0.0; extra == "all"
Requires-Dist: psutil>=5.9.0; extra == "all"
Requires-Dist: typing_extensions>=4.0.0; extra == "all"
Requires-Dist: black>=24.0.0; extra == "all"
Requires-Dist: flake8>=7.0.0; extra == "all"
Requires-Dist: mypy>=1.8.0; extra == "all"
Requires-Dist: sphinx>=7.0.0; extra == "all"
Requires-Dist: sphinx-rtd-theme>=2.0.0; extra == "all"
Requires-Dist: line-bot-sdk>=3.0.0; extra == "all"
Dynamic: author
Dynamic: author-email
Dynamic: classifier
Dynamic: description
Dynamic: description-content-type
Dynamic: home-page
Dynamic: keywords
Dynamic: license
Dynamic: license-file
Dynamic: platform
Dynamic: project-url
Dynamic: provides-extra
Dynamic: requires-dist
Dynamic: requires-python
Dynamic: summary
